{
  "id": "websocket-voice",
  "uiHints": {
    "port": {
      "label": "WebSocket Port",
      "help": "Port the voice WebSocket server listens on. Default: 8765."
    },
    "authSecret": {
      "label": "Authentication Secret",
      "help": "Optional shared secret. Clients must send ?token=<secret> on connect.",
      "sensitive": true
    },
    "sttProvider": {
      "label": "STT Provider Override",
      "help": "Override the default realtime transcription provider ID (e.g. deepgram)."
    },
    "ttsProvider": {
      "label": "TTS Provider Override",
      "help": "Override the default speech synthesis provider ID (e.g. elevenlabs)."
    }
  },
  "configSchema": {
    "type": "object",
    "additionalProperties": true
  }
}
